pesummary/.version
pesummary/__init__.py
pesummary/_version.py
pesummary/_version_helper.py
pesummary/cli/__init__.py
pesummary/cli/summaryclassification.py
pesummary/cli/summaryclean.py
pesummary/cli/summarycombine.py
pesummary/cli/summarycombine_posteriors.py
pesummary/cli/summarycompare.py
pesummary/cli/summarydetchar.py
pesummary/cli/summaryextract.py
pesummary/cli/summarygracedb.py
pesummary/cli/summaryjscompare.py
pesummary/cli/summarymodify.py
pesummary/cli/summarypages.py
pesummary/cli/summarypageslw.py
pesummary/cli/summarypipe.py
pesummary/cli/summaryplots.py
pesummary/cli/summarypublication.py
pesummary/cli/summaryrecreate.py
pesummary/cli/summaryreview.py
pesummary/cli/summarysplit.py
pesummary/cli/summarytest.py
pesummary/cli/summarytgr.py
pesummary/cli/summaryversion.py
pesummary/conf/__init__.py
pesummary/conf/caption.py
pesummary/conf/configuration.py
pesummary/conf/matplotlib_rcparams.sty
pesummary/core/__init__.py
pesummary/core/fetch.py
pesummary/core/finish.py
pesummary/core/reweight.py
pesummary/core/cli/__init__.py
pesummary/core/cli/actions.py
pesummary/core/cli/inputs.py
pesummary/core/cli/parser.py
pesummary/core/css/__init__.py
pesummary/core/css/font.css
pesummary/core/css/image_styles.css
pesummary/core/css/navbar.css
pesummary/core/css/side_bar.css
pesummary/core/css/table.css
pesummary/core/css/toggle.css
pesummary/core/css/watermark.css
pesummary/core/file/__init__.py
pesummary/core/file/injection.py
pesummary/core/file/mcmc.py
pesummary/core/file/meta_file.py
pesummary/core/file/read.py
pesummary/core/file/_lazy/__init__.py
pesummary/core/file/_lazy/base.py
pesummary/core/file/_lazy/hdf5.py
pesummary/core/file/formats/__init__.py
pesummary/core/file/formats/base_read.py
pesummary/core/file/formats/bilby.py
pesummary/core/file/formats/csv.py
pesummary/core/file/formats/dat.py
pesummary/core/file/formats/default.py
pesummary/core/file/formats/hdf5.py
pesummary/core/file/formats/ini.py
pesummary/core/file/formats/json.py
pesummary-1.6.0.dist-info/licenses/LICENSE.md
pesummary-1.6.0.dist-info/METADATA
pesummary-1.6.0.dist-info/WHEEL
pesummary-1.6.0.dist-info/entry_points.txt
pesummary-1.6.0.dist-info/top_level.txt
pesummary-1.6.0.dist-info/RECORD
